csvade2ics.py
csvade-1.0.0.dist-info/LICENSE
csvade-1.0.0.dist-info/METADATA
csvade-1.0.0.dist-info/WHEEL
csvade-1.0.0.dist-info/entry_points.txt
csvade-1.0.0.dist-info/top_level.txt
csvade-1.0.0.dist-info/RECORD
