Metadata-Version: 2.1
Name: csvade
Version: 1.0.0
Summary: Simple script to generate Calandar file (ICS) from CSV and ADE API.
Author: alexandrerbb
License: MIT License
Project-URL: Homepage, https://github.com/alexandrerbb/csvade
Project-URL: Source, https://github.com/alexandrerbb/csvade
Keywords: csv,ade,ics
Requires-Python: >=3.9
License-File: LICENSE
Requires-Dist: inquirerpy ==0.3.4
Requires-Dist: pyade ==0.0.2
Requires-Dist: ics ==0.7.2
